ACKS.txt
CHANGES.txt
LICENSE.txt
MANIFEST.in
README.txt
pyproject.toml
setup.py
Quixote.egg-info/PKG-INFO
Quixote.egg-info/SOURCES.txt
Quixote.egg-info/dependency_links.txt
Quixote.egg-info/top_level.txt
doc/CHANGES_24.txt
doc/INSTALL.html
doc/INSTALL.txt
doc/LICENSE_24.txt
doc/Makefile
doc/PTL.html
doc/PTL.txt
doc/default.css
doc/demo.html
doc/demo.txt
doc/docutils.css
doc/form2conversion.html
doc/form2conversion.txt
doc/multi-threaded.html
doc/multi-threaded.txt
doc/programming.html
doc/programming.txt
doc/session-mgmt.html
doc/session-mgmt.txt
doc/static-files.html
doc/static-files.txt
doc/upgrading.html
doc/upgrading.txt
doc/web-server.html
doc/web-server.txt
doc/web-services.html
doc/web-services.txt
doc/widgets.html
doc/widgets.txt
doc/win32.html
doc/win32.txt
doc/wsgi.html
doc/wsgi.txt
quixote/__init__.py
quixote/__main__.py
quixote/_version.py
quixote/config.py
quixote/directory.py
quixote/errors.py
quixote/http_request.py
quixote/http_response.py
quixote/logger.py
quixote/publish.py
quixote/publish1.py
quixote/sendmail.py
quixote/session.py
quixote/util.py
quixote/wsgi.py
quixote/demo/__init__.py
quixote/demo/altdemo.py
quixote/demo/extras.ptl
quixote/demo/forms.ptl
quixote/demo/integers.ptl
quixote/demo/mini_demo.py
quixote/demo/root.ptl
quixote/form/__init__.py
quixote/form/compatibility.py
quixote/form/css.py
quixote/form/form.py
quixote/form/widget.py
quixote/form1/__init__.py
quixote/form1/form.py
quixote/form1/widget.py
quixote/html/__init__.py
quixote/html/_c_htmltext.c
quixote/html/_py_htmltext.py
quixote/html/qpy_templateio.py
quixote/html/test/test_html.py
quixote/ptl/__init__.py
quixote/ptl/install.py
quixote/ptl/ptl_compile.py
quixote/ptl/ptl_import.py
quixote/ptl/ptl_parse.py
quixote/ptl/ptlrun.py
quixote/ptl/qx_distutils.py
quixote/ptl/test/test_ptl.py
quixote/server/__init__.py
quixote/server/cgi_server.py
quixote/server/scgi_server.py
quixote/server/simple_server.py
quixote/server/systemd_socket.py
quixote/server/threaded_server.py
quixote/server/util.py
quixote/server/wsgi_server.py
quixote/test/__init__.py
quixote/test/test_request.py
quixote/test/ua_test.py
